fetchmovie/__init__.py
fetchmovie/app.py
fetchmovie/data/bbt.yaml
fetchmovie/sites/__init__.py
fetchmovie/sites/_chrome.py
fetchmovie/sites/bbt.py
fetchmovie-0.0.1.3.dist-info/LICENSE
fetchmovie-0.0.1.3.dist-info/METADATA
fetchmovie-0.0.1.3.dist-info/WHEEL
fetchmovie-0.0.1.3.dist-info/entry_points.txt
fetchmovie-0.0.1.3.dist-info/top_level.txt
fetchmovie-0.0.1.3.dist-info/RECORD
