Metadata-Version: 2.1
Name: fetchmovie
Version: 0.0.1.3
Summary: movie searcher
Home-page: https://github.com/coghost/fetchmovie
Author: lihe
Author-email: imanux@sina.com
License: GPL
Project-URL: Bug Reports, https://github.com/coghost/fetchmovie/issues
Project-URL: Source, https://github.com/coghost/fetchmovie
Keywords: movie,movie searcher,douban
Platform: UNKNOWN
Classifier: Programming Language :: Python :: 3.7
Classifier: Programming Language :: Python :: 3.8
Requires-Python: >=3.7
Requires-Dist: icraw
Requires-Dist: iparse
Requires-Dist: lxml
Requires-Dist: click
Requires-Dist: urllib3
Requires-Dist: vto
